physis/__init__.py
physis/test.py
physis/test.so
pyhsis-1.2.5.dist-info/LICENSE
pyhsis-1.2.5.dist-info/METADATA
pyhsis-1.2.5.dist-info/WHEEL
pyhsis-1.2.5.dist-info/top_level.txt
pyhsis-1.2.5.dist-info/RECORD
